odoo/addons/shopfloor_reception_packaging_dimension_mobile/README.rst
odoo/addons/shopfloor_reception_packaging_dimension_mobile/__init__.py
odoo/addons/shopfloor_reception_packaging_dimension_mobile/__manifest__.py
odoo/addons/shopfloor_reception_packaging_dimension_mobile/i18n/shopfloor_reception_packaging_dimension_mobile.pot
odoo/addons/shopfloor_reception_packaging_dimension_mobile/readme/CONTRIBUTORS.rst
odoo/addons/shopfloor_reception_packaging_dimension_mobile/readme/DESCRIPTION.rst
odoo/addons/shopfloor_reception_packaging_dimension_mobile/static/description/icon.png
odoo/addons/shopfloor_reception_packaging_dimension_mobile/static/description/index.html
odoo/addons/shopfloor_reception_packaging_dimension_mobile/static/src/scenario/reception_packaging_dimension.js
odoo/addons/shopfloor_reception_packaging_dimension_mobile/templates/assets.xml
odoo14_addon_shopfloor_reception_packaging_dimension_mobile-14.0.1.1.0.dist-info/METADATA
odoo14_addon_shopfloor_reception_packaging_dimension_mobile-14.0.1.1.0.dist-info/WHEEL
odoo14_addon_shopfloor_reception_packaging_dimension_mobile-14.0.1.1.0.dist-info/top_level.txt
odoo14_addon_shopfloor_reception_packaging_dimension_mobile-14.0.1.1.0.dist-info/RECORD
